libgmock.a
libgmock_main.a
libgtest.a
libgtest_main.a
flare/__init__.py
flare/env.py
flare/gp.py
flare/gp_algebra.py
flare/gp_from_aimd.py
flare/learning_protocol.py
flare/md.py
flare/otf.py
flare/otf_parser.py
flare/output.py
flare/parameters.py
flare/predict.py
flare/rbcm.py
flare/struc.py
flare/ase/__init__.py
flare/ase/atoms.py
flare/ase/calculator.py
flare/ase/dft.py
flare/ase/nosehoover.py
flare/ase/npt.py
flare/ase/otf.py
flare/dft_interface/__init__.py
flare/dft_interface/cp2k_util.py
flare/dft_interface/qe_util.py
flare/dft_interface/vasp_util.py
flare/kernels/__init__.py
flare/kernels/coordination_mc_simple.py
flare/kernels/cutoffs.py
flare/kernels/kernels.py
flare/kernels/mc_3b_sepcut.py
flare/kernels/mc_mb_sepcut.py
flare/kernels/mc_sephyps.py
flare/kernels/mc_simple.py
flare/kernels/sc.py
flare/kernels/three_body_mc_simple.py
flare/kernels/two_body_mc_simple.py
flare/kernels/utils.py
flare/lammps/__init__.py
flare/lammps/lammps_calculator.py
flare/mgp/__init__.py
flare/mgp/cubic_splines_numba.py
flare/mgp/grid_kernels.py
flare/mgp/map2b.py
flare/mgp/map3b.py
flare/mgp/mapxb.py
flare/mgp/mgp.py
flare/mgp/splines_methods.py
flare/utils/__init__.py
flare/utils/element_coder.py
flare/utils/env_getarray.py
flare/utils/flare_io.py
flare/utils/learner.py
flare/utils/md_helper.py
flare/utils/parameter_helper.py
mir_flare-0.2.4.dist-info/LICENSE
mir_flare-0.2.4.dist-info/METADATA
mir_flare-0.2.4.dist-info/WHEEL
mir_flare-0.2.4.dist-info/top_level.txt
mir_flare-0.2.4.dist-info/RECORD
