Metadata-Version: 2.1
Name: mir-flare
Version: 0.2.4
Summary: Fast Learning of Atomistic Rare Events
Home-page: https://github.com/mir-group/flare
Author: Materials Intelligence Research
Author-email: mir@g.harvard.edu
License: MIT
Platform: UNKNOWN
Classifier: License :: OSI Approved :: MIT License
Classifier: Topic :: Scientific/Engineering :: Physics
Classifier: Topic :: Scientific/Engineering :: Artificial Intelligence
Classifier: Development Status :: 4 - Beta
Requires-Python: >=3.6
Requires-Dist: numpy (<=1.20.3)
Requires-Dist: scipy
Requires-Dist: memory-profiler
Requires-Dist: numba
Requires-Dist: ase
Requires-Dist: nptyping
Requires-Dist: nbsphinx
Requires-Dist: IPython
Requires-Dist: pytest (>=4.6)
Requires-Dist: pytest-mock
